autotx/AutoTx.py
autotx/__init__.py
autotx/agents/DelegateResearchTokensAgent.py
autotx/agents/ExampleAgent.py
autotx/agents/ResearchTokensAgent.py
autotx/agents/SendTokensAgent.py
autotx/agents/SwapTokensAgent.py
autotx/agents/__init__.py
autotx/autotx_agent.py
autotx/autotx_tool.py
autotx/build_check.py
autotx/chain_fork.py
autotx/cli.py
autotx/db.py
autotx/eth_address.py
autotx/get_env_vars.py
autotx/helper_agents/__init__.py
autotx/helper_agents/clarifier.py
autotx/helper_agents/manager.py
autotx/helper_agents/user_proxy.py
autotx/intents.py
autotx/load_tokens.py
autotx/models.py
autotx/server.py
autotx/setup.py
autotx/tests/agents/regression/token/test_tokens_regression.py
autotx/tests/agents/token/research/test_advanced.py
autotx/tests/agents/token/research/test_research.py
autotx/tests/agents/token/research/test_research_and_swap.py
autotx/tests/agents/token/research/test_research_swap_and_send.py
autotx/tests/agents/token/send/test_send.py
autotx/tests/agents/token/test_swap.py
autotx/tests/agents/token/test_swap_and_send.py
autotx/tests/api/test_connect.py
autotx/tests/api/test_send_transactions.py
autotx/tests/api/test_tasks.py
autotx/tests/conftest.py
autotx/tests/integration/test_swap.py
autotx/token.py
autotx/transactions.py
autotx/utils/LlamaClient.py
autotx/utils/__init__.py
autotx/utils/color.py
autotx/utils/configuration.py
autotx/utils/constants.py
autotx/utils/ethereum/SafeManager.py
autotx/utils/ethereum/__init__.py
autotx/utils/ethereum/agent_account.py
autotx/utils/ethereum/build_approve_erc20.py
autotx/utils/ethereum/build_transfer_erc20.py
autotx/utils/ethereum/build_transfer_native.py
autotx/utils/ethereum/cache.py
autotx/utils/ethereum/cached_safe_address.py
autotx/utils/ethereum/chain_short_names.py
autotx/utils/ethereum/constants.py
autotx/utils/ethereum/deploy_multicall.py
autotx/utils/ethereum/deploy_safe_with_create2.py
autotx/utils/ethereum/erc20_abi.py
autotx/utils/ethereum/get_erc20_balance.py
autotx-0.1.3.dist-info/LICENSE
autotx-0.1.3.dist-info/METADATA
autotx-0.1.3.dist-info/WHEEL
autotx-0.1.3.dist-info/entry_points.txt
autotx-0.1.3.dist-info/RECORD
