Metadata-Version: 2.1
Name: autotx
Version: 0.1.3
Summary: 
Author: Nestor Amesty
Author-email: nestor09amesty@gmail.com
Requires-Python: >=3.10,<3.13
Classifier: Programming Language :: Python :: 3
Classifier: Programming Language :: Python :: 3.10
Classifier: Programming Language :: Python :: 3.11
Requires-Dist: click (>=8.1.7,<9.0.0)
Requires-Dist: coingecko (>=0.13,<0.14)
Requires-Dist: eth-account (>=0.11.0,<0.12.0)
Requires-Dist: fastapi (>=0.111.0,<0.112.0)
Requires-Dist: llama-cpp-python (>=0.2.78,<0.3.0)
Requires-Dist: pyautogen (>=0.2.27,<0.3.0)
Requires-Dist: pyright (>=1.1.350,<2.0.0)
Requires-Dist: python-dotenv (>=1.0.0,<2.0.0)
Requires-Dist: requests (>=2.31.0,<3.0.0)
Requires-Dist: safe-eth-py (>=5.8.0,<6.0.0)
Requires-Dist: supabase (>=2.5.0,<3.0.0)
Requires-Dist: uvicorn (>=0.29.0,<0.30.0)
Requires-Dist: web3 (>=6.19.0,<7.0.0)
